snowflake_cli_nextflow-0.2.0.dist-info/licenses/LICENSE
snowflakecli/nextflow/__init__.py
snowflakecli/nextflow/commands.py
snowflakecli/nextflow/manager.py
snowflakecli/nextflow/plugin_spec.py
snowflakecli/nextflow/service_spec.py
snowflakecli/nextflow/config/parser.py
snowflakecli/nextflow/image/__init__.py
snowflakecli/nextflow/image/commands.py
snowflakecli/nextflow/image/manager.py
snowflakecli/nextflow/wss/__init__.py
snowflakecli/nextflow/wss/websocket_client.py
snowflakecli/nextflow/wss/websocket_exceptions.py
snowflake_cli_nextflow-0.2.0.dist-info/METADATA
snowflake_cli_nextflow-0.2.0.dist-info/WHEEL
snowflake_cli_nextflow-0.2.0.dist-info/entry_points.txt
snowflake_cli_nextflow-0.2.0.dist-info/top_level.txt
snowflake_cli_nextflow-0.2.0.dist-info/RECORD
