Metadata-Version: 2.4
Name: snowflake-cli-nextflow
Version: 0.2.0
Summary: A Snowflake CLI plugin that enables running Nextflow workflows directly in Snowpark Container Services
Author-email: Haowei Yu <haowei.yu@snowflake.com>
License: Apache-2.0
Project-URL: Homepage, https://github.com/Snowflake-Labs/snowflake-cli-nextflow
Project-URL: Repository, https://github.com/Snowflake-Labs/snowflake-cli-nextflow
Project-URL: Documentation, https://github.com/Snowflake-Labs/snowflake-cli-nextflow
Project-URL: Issues, https://github.com/Snowflake-Labs/snowflake-cli-nextflow/issues
Keywords: snowflake,cli,plugin,nextflow,workflow,bioinformatics,snowpark,container-services
Classifier: Development Status :: 3 - Alpha
Classifier: Intended Audience :: Developers
Classifier: Intended Audience :: Science/Research
Classifier: License :: OSI Approved :: Apache Software License
Classifier: Operating System :: OS Independent
Classifier: Programming Language :: Python :: 3
Classifier: Programming Language :: Python :: 3.10
Classifier: Programming Language :: Python :: 3.11
Classifier: Programming Language :: Python :: 3.12
Classifier: Topic :: Scientific/Engineering :: Bio-Informatics
Classifier: Topic :: Software Development :: Libraries :: Python Modules
Classifier: Topic :: Database
Classifier: Topic :: System :: Distributed Computing
Requires-Python: >=3.10
License-File: LICENSE
Requires-Dist: snowflake-cli>=3.10.0
Requires-Dist: pyyaml
Requires-Dist: websockets
Requires-Dist: docker
Requires-Dist: groovy-parser
Dynamic: license-file
